aleksis/apps/chronos/__init__.py
aleksis/apps/chronos/admin.py
aleksis/apps/chronos/apps.py
aleksis/apps/chronos/frontend/components/AmendLesson.vue
aleksis/apps/chronos/frontend/components/LessonEventLinkIterator.vue
aleksis/apps/chronos/frontend/components/LessonEventOldNew.vue
aleksis/apps/chronos/frontend/components/LessonEventSubject.vue
aleksis/apps/chronos/frontend/components/LessonInformation.vue
aleksis/apps/chronos/frontend/components/LessonRelatedObjectChip.vue
aleksis/apps/chronos/frontend/components/NoTimetableCard.vue
aleksis/apps/chronos/frontend/components/SelectTimetable.vue
aleksis/apps/chronos/frontend/components/Substitutions.vue
aleksis/apps/chronos/frontend/components/Timetable.vue
aleksis/apps/chronos/frontend/components/TimetableWrapper.vue
aleksis/apps/chronos/frontend/components/amendLesson.graphql
aleksis/apps/chronos/frontend/components/calendar_feeds/details/LessonDetails.vue
aleksis/apps/chronos/frontend/components/calendar_feeds/details/SupervisionDetails.vue
aleksis/apps/chronos/frontend/components/calendar_feeds/event_bar/LessonEventBar.vue
aleksis/apps/chronos/frontend/components/calendar_feeds/event_bar/SupervisionEventBar.vue
aleksis/apps/chronos/frontend/components/calendar_feeds/mixins/lessonEvent.js
aleksis/apps/chronos/frontend/components/substitutions/SubstitutionCard.vue
aleksis/apps/chronos/frontend/components/substitutions/SubstitutionInformation.vue
aleksis/apps/chronos/frontend/components/substitutions/SubstitutionLoader.vue
aleksis/apps/chronos/frontend/components/substitutions/SubstitutionOverview.vue
aleksis/apps/chronos/frontend/components/substitutions/SubstitutionStatus.vue
aleksis/apps/chronos/frontend/components/substitutions.graphql
aleksis/apps/chronos/frontend/components/timetableTypes.js
aleksis/apps/chronos/frontend/components/timetables.graphql
aleksis/apps/chronos/frontend/index.js
aleksis/apps/chronos/frontend/messages/ar.json
aleksis/apps/chronos/frontend/messages/de.json
aleksis_app_chronos-4.0.1.dist-info/LICENCE.rst
aleksis_app_chronos-4.0.1.dist-info/METADATA
aleksis_app_chronos-4.0.1.dist-info/WHEEL
aleksis_app_chronos-4.0.1.dist-info/entry_points.txt
aleksis_app_chronos-4.0.1.dist-info/RECORD
