Metadata-Version: 2.3
Name: AlekSIS-App-Chronos
Version: 4.0.1
Summary: AlekSIS (School Information System) — App Χρόνος (digital timetables)
License: EUPL-1.2-or-later
Keywords: SIS,education,school,timetable,plans
Author: Dominik George
Author-email: dominik.george@teckids.org
Maintainer: Jonathan Weth
Maintainer-email: jonathan.weth@teckids.org
Requires-Python: >=3.10,<4.0
Classifier: Development Status :: 5 - Production/Stable
Classifier: Environment :: Web Environment
Classifier: Framework :: Django :: 3.0
Classifier: Intended Audience :: Education
Classifier: License :: Other/Proprietary License
Classifier: Programming Language :: Python :: 3
Classifier: Programming Language :: Python :: 3.10
Classifier: Programming Language :: Python :: 3.11
Classifier: Programming Language :: Python :: 3.12
Classifier: Programming Language :: Python :: 3.13
Classifier: Topic :: Education
Classifier: Typing :: Typed
Requires-Dist: aleksis-app-cursus (>=1.0.0,<2.0.0)
Requires-Dist: aleksis-app-kolego (>=1.0.0,<2.0.0)
Requires-Dist: aleksis-app-resint (>=4.0.0,<5.0.0)
Requires-Dist: aleksis-core (>=4.0.0,<5.0.0)
Requires-Dist: calendarweek (>=0.5.0,<0.6.0)
Project-URL: Documentation, https://aleksis.org/AlekSIS/docs/html/
Project-URL: Homepage, https://aleksis.org
Project-URL: Repository, https://edugit.org/AlekSIS/official/AlekSIS-App-Chronos
